pyttman_openai_plugin/__init__.py
pyttman_openai_plugin/plugin.py
pyttman_plugin_openai-2.0.1.dist-info/METADATA
pyttman_plugin_openai-2.0.1.dist-info/WHEEL
pyttman_plugin_openai-2.0.1.dist-info/top_level.txt
pyttman_plugin_openai-2.0.1.dist-info/RECORD
